scruby/__init__.py
scruby/aggregation.py
scruby/db.py
scruby/errors.py
scruby/mixins/__init__.py
scruby/mixins/collection.py
scruby/mixins/count.py
scruby/mixins/custom_task.py
scruby/mixins/delete.py
scruby/mixins/find.py
scruby/mixins/keys.py
scruby/mixins/update.py
scruby/py.typed
scruby/settings.py
scruby-0.33.0.dist-info/licenses/LICENSE
scruby-0.33.0.dist-info/WHEEL
scruby-0.33.0.dist-info/METADATA
scruby-0.33.0.dist-info/RECORD
