Metadata-Version: 2.4
Name: scruby
Version: 0.33.0
Summary: Asynchronous library for building and managing a hybrid database, by scheme of key-value.
Keywords: database,store,scruby,async
Author: kebasyaty
Author-email: kebasyaty <kebasyaty@gmail.com>
License-Expression: GPL-3.0-or-later
License-File: LICENSE
Classifier: Development Status :: 4 - Beta
Classifier: Intended Audience :: Developers
Classifier: License :: OSI Approved :: GNU General Public License v3 or later (GPLv3+)
Classifier: Operating System :: MacOS :: MacOS X
Classifier: Operating System :: Microsoft :: Windows
Classifier: Operating System :: POSIX
Classifier: Operating System :: POSIX :: Linux
Classifier: Programming Language :: Python :: 3
Classifier: Programming Language :: Python :: 3 :: Only
Classifier: Programming Language :: Python :: 3.12
Classifier: Programming Language :: Python :: 3.13
Classifier: Programming Language :: Python :: 3.14
Classifier: Programming Language :: Python :: Implementation :: CPython
Classifier: Topic :: Software Development :: Libraries
Classifier: Topic :: Software Development :: Libraries :: Python Modules
Classifier: Topic :: Database
Classifier: Typing :: Typed
Requires-Dist: anyio>=4.10.0
Requires-Dist: orjson>=3.11.3
Requires-Dist: pydantic[email,timezone]>=2.11.7
Requires-Dist: pydantic-extra-types>=2.10.5
Requires-Dist: phonenumbers>=9.0.13
Requires-Dist: xloft>=0.9.8
Requires-Python: >=3.12, <4.0
Project-URL: Bug Tracker, https://github.com/kebasyaty/scruby/issues
Project-URL: Changelog, https://github.com/kebasyaty/scruby/blob/v0/CHANGELOG.md
Project-URL: Homepage, https://kebasyaty.github.io/scruby/
Project-URL: Repository, https://github.com/kebasyaty/scruby
Project-URL: Source, https://github.com/kebasyaty/scruby
